<?xml version="1.0" encoding="utf-8"?>
<!-- Sid Meier's Civilization V -->
<!-- Copyright Firaxis Games 2010 -->
<!-- -->
<!-- Game Text Objects -->
<GameData>
	<Language_en_US>
		<Row Tag="TXT_KEY_BUILDING_ACADEMY">
			<Text>Academy</Text>
            <Gender>neuter:an</Gender>
		</Row>
		<Row Tag="TXT_KEY_BUILDING_ANGKOR_WAT">
			<Text>Angkor Wat</Text>
		</Row>
		<Row Tag="TXT_KEY_BUILDING_ARMORY">
			<Text>Armory</Text>
            <Gender>neuter:an</Gender>
		</Row>
		<Row Tag="TXT_KEY_BUILDING_ARSENAL">
			<Text>Arsenal</Text>
            <Gender>neuter:an</Gender>
		</Row>
		<Row Tag="TXT_KEY_BUILDING_BANK">
			<Text>Bank</Text>
		</Row>
		<Row Tag="TXT_KEY_BUILDING_BARRACKS">
			<Text>Barracks</Text>
            <Plurality>2</Plurality>
		</Row>
		<Row Tag="TXT_KEY_BUILDING_BIG_BEN">
			<Text>Big Ben</Text>
		</Row>
		<Row Tag="TXT_KEY_BUILDING_BRANDENBURG_GATE">
			<Text>Brandenburg Gate</Text>
		</Row>
		<Row Tag="TXT_KEY_BUILDING_BROADCAST_TOWER">
			<Text>Broadcast Tower</Text>
		</Row>
		<Row Tag="TXT_KEY_BUILDING_CASTLE">
			<Text>Castle</Text>
		</Row>
		<Row Tag="TXT_KEY_BUILDING_CHICHEN_ITZA">
			<Text>Chichen Itza</Text>
		</Row>
		<Row Tag="TXT_KEY_BUILDING_COLOSSEUM">
			<Text>Colosseum</Text>
		</Row>
		<Row Tag="TXT_KEY_BUILDING_COLOSSUS">
			<Text>The Colossus</Text>
		</Row>
		<Row Tag="TXT_KEY_BUILDING_CRISTO_REDENTOR">
			<Text>Cristo Redentor</Text>
		</Row>
		<Row Tag="TXT_KEY_BUILDING_SEAPORT">
			<Text>Seaport</Text>
		</Row>
		<Row Tag="TXT_KEY_BUILDING_EIFFEL_TOWER">
			<Text>Eiffel Tower</Text>
		</Row>
		<Row Tag="TXT_KEY_BUILDING_FACTORY">
			<Text>Factory</Text>
		</Row>
		<Row Tag="TXT_KEY_BUILDING_FORBIDDEN_PALACE">
			<Text>The Forbidden Palace</Text>
		</Row>
		<Row Tag="TXT_KEY_BUILDING_FORGE">
			<Text>Forge</Text>
		</Row>
		<Row Tag="TXT_KEY_BUILDING_GRANARY">
			<Text>Granary</Text>
		</Row>
		<Row Tag="TXT_KEY_BUILDING_GREAT_LIBRARY">
			<Text>The Great Library</Text>
		</Row>
		<Row Tag="TXT_KEY_BUILDING_GREAT_LIGHTHOUSE">
			<Text>The Great Lighthouse</Text>
		</Row>
		<Row Tag="TXT_KEY_BUILDING_GREAT_WALL">
			<Text>The Great Wall</Text>
		</Row>
		<Row Tag="TXT_KEY_BUILDING_GROCER">
			<Text>Grocer</Text>
		</Row>
		<Row Tag="TXT_KEY_BUILDING_HAGIA_SOPHIA">
			<Text>The Hagia Sophia</Text>
		</Row>
		<Row Tag="TXT_KEY_BUILDING_HANGING_GARDEN">
			<Text>The Hanging Gardens</Text>
		</Row>
		<Row Tag="TXT_KEY_BUILDING_HARBOR">
			<Text>Harbor</Text>
		</Row>
		<Row Tag="TXT_KEY_BUILDING_HEROIC_EPIC">
			<Text>Heroic Epic</Text>
		</Row>
		<Row Tag="TXT_KEY_BUILDING_HIMEJI_CASTLE">
			<Text>Himeji Castle</Text>
		</Row>
		<Row Tag="TXT_KEY_BUILDING_HYDRO_PLANT">
			<Text>Hydro Plant</Text>
		</Row>
		<Row Tag="TXT_KEY_BUILDING_KREMLIN">
			<Text>The Kremlin</Text>
		</Row>
		<Row Tag="TXT_KEY_BUILDING_LABORATORY">
			<Text>Research Lab</Text>
		</Row>
		<Row Tag="TXT_KEY_BUILDING_LIBRARY">
			<Text>Library</Text>
		</Row>
		<Row Tag="TXT_KEY_BUILDING_LIGHTHOUSE">
			<Text>Lighthouse</Text>
		</Row>
		<Row Tag="TXT_KEY_BUILDING_LOUVRE">
			<Text>The Louvre</Text>
		</Row>
		<Row Tag="TXT_KEY_BUILDING_MACHU_PICHU">
			<Text>Machu Picchu</Text>
		</Row>
		<Row Tag="TXT_KEY_BUILDING_MARKET">
			<Text>Market</Text>
		</Row>
		<Row Tag="TXT_KEY_BUILDING_MILITARY_ACADEMY">
			<Text>Military Academy</Text>
		</Row>
		<Row Tag="TXT_KEY_BUILDING_MILITARY_BASE">
			<Text>Military Base</Text>
		</Row>
		<Row Tag="TXT_KEY_BUILDING_MINT">
			<Text>Mint</Text>
		</Row>
		<Row Tag="TXT_KEY_BUILDING_MUSEUM">
			<Text>Museum</Text>
		</Row>
		<Row Tag="TXT_KEY_BUILDING_NATIONAL_COLLEGE">
			<Text>National College</Text>
		</Row>
		<Row Tag="TXT_KEY_BUILDING_NATIONAL_EPIC">
			<Text>National Epic</Text>
		</Row>
		<Row Tag="TXT_KEY_BUILDING_CIRCUS_MAXIMUS">
			<Text>Circus Maximus</Text>
		</Row>
		<Row Tag="TXT_KEY_BUILDING_NATIONAL_TREASURY">
			<Text>National Treasury</Text>
		</Row>
		<Row Tag="TXT_KEY_PROJECT_UTOPIA_PROJECT">
			<Text>Utopia Project</Text>
		</Row>
		<Row Tag="TXT_KEY_BUILDING_NUCLEAR_PLANT">
			<Text>Nuclear Plant</Text>
		</Row>
		<Row Tag="TXT_KEY_BUILDING_NOTRE_DAME">
			<Text>Notre Dame</Text>
		</Row>
		<Row Tag="TXT_KEY_BUILDING_OPERA_HOUSE">
			<Text>Opera House</Text>
            <Gender>neuter:an</Gender>
		</Row>
		<Row Tag="TXT_KEY_BUILDING_ORACLE">
			<Text>The Oracle</Text>
		</Row>
		<Row Tag="TXT_KEY_BUILDING_PALACE">
			<Text>Palace</Text>
		</Row>
		<Row Tag="TXT_KEY_BUILDING_PENTAGON">
			<Text>Pentagon</Text>
		</Row>
		<Row Tag="TXT_KEY_BUILDING_PARK">
			<Text>Park</Text>
		</Row>
		<Row Tag="TXT_KEY_BUILDING_PORCELAIN_TOWER">
			<Text>The Porcelain Tower</Text>
		</Row>
		<Row Tag="TXT_KEY_BUILDING_OBSERVATORY">
			<Text>Observatory</Text>
		</Row>
		<Row Tag="TXT_KEY_BUILDING_PYRAMID">
			<Text>The Pyramids</Text>
            <Plurality>2</Plurality>
		</Row>
		<Row Tag="TXT_KEY_BUILDING_SISTINE_CHAPEL">
			<Text>Sistine Chapel</Text>
		</Row>
		<Row Tag="TXT_KEY_BUILDING_SOLAR_PLANT">
			<Text>Solar Plant</Text>
		</Row>
		<Row Tag="TXT_KEY_BUILDING_SPACESHIP_FACTORY">
			<Text>Spaceship Factory</Text>
		</Row>
		<Row Tag="TXT_KEY_BUILDING_STABLE">
			<Text>Stable</Text>
		</Row>
		<Row Tag="TXT_KEY_BUILDING_STATUE_OF_LIBERTY">
			<Text>Statue of Liberty</Text>
		</Row>
		<Row Tag="TXT_KEY_BUILDING_STONEHENGE">
			<Text>Stonehenge</Text>
		</Row>
		<Row Tag="TXT_KEY_BUILDING_TAJ_MAHAL">
			<Text>Taj Mahal</Text>
		</Row>
		<Row Tag="TXT_KEY_BUILDING_TEMPLE">
			<Text>Temple</Text>
		</Row>
		<Row Tag="TXT_KEY_BUILDING_THEATRE">
			<Text>Theatre</Text>
		</Row>
		<Row Tag="TXT_KEY_BUILDING_COURTHOUSE">
			<Text>Courthouse</Text>
		</Row>
		<Row Tag="TXT_KEY_BUILDING_UNITED_NATIONS">
			<Text>United Nations</Text>
		</Row>
		<Row Tag="TXT_KEY_BUILDING_UNIVERSITY">
			<Text>University</Text>
		</Row>
		<Row Tag="TXT_KEY_BUILDING_WALLS">
			<Text>Walls</Text>
            <Plurality>2</Plurality>
		</Row>
		<Row Tag="TXT_KEY_BUILDING_WATERMILL">
			<Text>Water Mill</Text>
		</Row>
		<Row Tag="TXT_KEY_BUILDING_WINDMILL">
			<Text>Windmill</Text>
		</Row>
		<Row Tag="TXT_KEY_BUILDING_WORKSHOP">
			<Text>Workshop</Text>
		</Row>
		<Row Tag="TXT_KEY_BUILDING_MUGHAL_FORT_DESC">
			<Text>Mughal Fort</Text>
		</Row>
		<Row Tag="TXT_KEY_BUILDING_AQUEDUCT">
			<Text>Aqueduct</Text>
		</Row>
		<Row Tag="TXT_KEY_BUILDING_HOSPITAL">
			<Text>Hospital</Text>
		</Row>
		<Row Tag="TXT_KEY_BUILDING_MEDICAL_LAB">
			<Text>Medical Lab</Text>
		</Row>
		<Row Tag="TXT_KEY_BUILDING_STOCK_EXCHANGE">
			<Text>Stock Exchange</Text>
		</Row>
		<Row Tag="TXT_KEY_BUILDING_PUBLIC_SCHOOL">
			<Text>Public School</Text>
		</Row>
		<Row Tag="TXT_KEY_BUILDING_KREPOST_DESC">
			<Text>Krepost</Text>
		</Row>
		<Row Tag="TXT_KEY_BUILDING_CIRCUS">
			<Text>Circus</Text>
		</Row>
		<Row Tag="TXT_KEY_BUILDING_GARDEN">
			<Text>Garden</Text>
		</Row>
		<Row Tag="TXT_KEY_BUILDING_IRONWORKS">
			<Text>Ironworks</Text>
            <Gender>neuter:an</Gender>
            <Plurality>2</Plurality>
		</Row>
		<Row Tag="TXT_KEY_BUILDING_OXFORD_UNIVERSITY">
			<Text>Oxford University</Text>
		</Row>
		<Row Tag="TXT_KEY_BUILDING_HERMITAGE">
			<Text>Hermitage</Text>
		</Row>
		<Row Tag="TXT_KEY_BUILDING_STONE_WORKS">
			<Text>Stone Works</Text>
		</Row>
	</Language_en_US>
</GameData>